certbot_dns_simply/__init__.py
certbot_dns_simply/dns_simply.py
certbot_dns_simply/dns_simply_test.py
certbot_dns_simply-0.1.2.dist-info/LICENSE
certbot_dns_simply-0.1.2.dist-info/METADATA
certbot_dns_simply-0.1.2.dist-info/WHEEL
certbot_dns_simply-0.1.2.dist-info/entry_points.txt
certbot_dns_simply-0.1.2.dist-info/top_level.txt
certbot_dns_simply-0.1.2.dist-info/RECORD
